ppctools/__init__.py
ppctools/network/__init__.py
ppctools/network/io.py
ppctools/terminal/__init__.py
ppctools/terminal/efrocolor.py
tests/__init__.py
tests/network/__init__.py
tests/network/test_io.py
ppctools-0.1.0.dist-info/LICENSE
ppctools-0.1.0.dist-info/METADATA
ppctools-0.1.0.dist-info/WHEEL
ppctools-0.1.0.dist-info/top_level.txt
ppctools-0.1.0.dist-info/RECORD
