Metadata-Version: 2.1
Name: ppctools
Version: 0.1.0
Summary: PPC tools for CTF tasks
Home-page: https://github.com/Dliwk/ppctools
Author: Roman Trapeznikov
Author-email: roma190505@yandex.ru
License: UNKNOWN
Platform: UNKNOWN
Classifier: Programming Language :: Python :: 3
Classifier: License :: Freeware
Requires-Python: >=3.6
